{
  "name": "pancakeswap",
  "timestamp": "2020-08-25T15:41:29.665Z",
  "version": {
    "major": 1,
    "minor": 3,
    "patch": 1
  },
  "tags": {},
  "logoURI": "/images/coins/wbnb.png",
  "keywords": ["pancake", "default"],
  "tokens": [
    {
      "name": "PuffyDogCoin",
      "symbol": "PUFFY",
      "address": "0x42873a833717753a8d77ad6d0a8710af2c66c052",
      "chainId": 56,
      "decimals": 9,
      "logoURI": "https://exchange.pancakeswap.finance/images/coins/0x42873a833717753a8d77ad6d0a8710af2c66c052.png"
    }
  ]
}
